README.rst
setup.cfg
setup.py
dpassgen/__init__.py
dpassgen.egg-info/PKG-INFO
dpassgen.egg-info/SOURCES.txt
dpassgen.egg-info/dependency_links.txt
dpassgen.egg-info/entry_points.txt
dpassgen.egg-info/top_level.txt