Metadata-Version: 1.0
Name: dpassgen
Version: 1.1
Summary: Generate passwords based on system dict, https://xkcd.com/936/
Home-page: https://xkcd.com/936/
Author: John Dulaney
Author-email: jdulaney@fedoraproject.org
License: GPLv3
Platform: UNKNOWN
